xontrib/distributed.py
xontrib_distributed-0.0.4.dist-info/LICENSE
xontrib_distributed-0.0.4.dist-info/WHEEL
xontrib_distributed-0.0.4.dist-info/METADATA
xontrib_distributed-0.0.4.dist-info/RECORD
