Metadata-Version: 2.1
Name: xontrib-distributed
Version: 0.0.4
Summary: The distributed parallel computing library hooks for xonsh
Home-page: https://github.com/xonsh/xontrib-distributed
License: MIT
Keywords: xontrib,xonsh
Author: Xonsh Dev
Author-email: jnoortheen@gmail.com
Requires-Python: >=3.8
Classifier: Intended Audience :: Developers
Classifier: License :: OSI Approved :: MIT License
Classifier: Natural Language :: English
Classifier: Operating System :: OS Independent
Classifier: Programming Language :: Python
Classifier: Programming Language :: Python :: 3
Classifier: Programming Language :: Python :: 3.10
Classifier: Programming Language :: Python :: 3.6
Classifier: Programming Language :: Python :: 3.7
Classifier: Programming Language :: Python :: 3.8
Classifier: Programming Language :: Python :: 3.9
Classifier: Topic :: System :: Shells
Classifier: Topic :: System :: System Shells
Classifier: Topic :: Terminals
Requires-Dist: distributed (>=2022.3.0)
Requires-Dist: xonsh (>=0.12)
Project-URL: Code, https://github.com/xonsh/xontrib-distributed
Project-URL: Documentation, https://github.com/xonsh/xontrib-distributed/blob/master/README.md
Project-URL: Issue tracker, https://github.com/xonsh/xontrib-distributed/issues
Project-URL: Repository, https://github.com/xonsh/xontrib-distributed
